affo_email_service/__init__.py
affo_email_service/application.py
affo_email_service/celery.py
affo_email_service/cli.py
affo_email_service/const.py
affo_email_service/extensions.py
affo_email_service/settings.py
affo_email_service/wsgi.py
affo_email_service/api/__init__.py
affo_email_service/api/exception.py
affo_email_service/api/message.py
affo_email_service/api/template.py
affo_email_service/api/unsubscribe.py
affo_email_service/migrations/README
affo_email_service/migrations/alembic.ini
affo_email_service/migrations/env.py
affo_email_service/migrations/script.py.mako
affo_email_service/migrations/versions/b96e7daa1cdb_.py
affo_email_service/models/__init__.py
affo_email_service/models/message.py
affo_email_service/models/unsubscribe.py
affo_email_service/routes/__init__.py
affo_email_service/routes/feedback.py
affo_email_service/routes/template.py
affo_email_service/routes/unsubscribe.py
affo_email_service/services/__init__.py
affo_email_service/services/email.py
affo_email_service/spec/openapi.yaml
affo_email_service/tasks/__init__.py
affo_email_service/tasks/email.py
affo_email_service-1.0.3.dist-info/LICENSE
affo_email_service-1.0.3.dist-info/METADATA
affo_email_service-1.0.3.dist-info/WHEEL
affo_email_service-1.0.3.dist-info/entry_points.txt
affo_email_service-1.0.3.dist-info/top_level.txt
affo_email_service-1.0.3.dist-info/RECORD
